test/__init__.py
test/test_tphate.py
tphate/__init__.py
tphate/api.py
tphate/base.py
tphate/graphs.py
tphate/matrix.py
tphate/mds.py
tphate/tphate.py
tphate/utils.py
tphate/version.py
tphate/vne.py
tphate-1.2.1.dist-info/licenses/LICENSE.md
tphate-1.2.1.dist-info/METADATA
tphate-1.2.1.dist-info/WHEEL
tphate-1.2.1.dist-info/top_level.txt
tphate-1.2.1.dist-info/RECORD
