Metadata-Version: 2.4
Name: TPHATE
Version: 1.2.1
Summary: Temporal PHATE (TPHATE) is a python package for learning robust manifold representations of timeseries data with high temporal autocorrelation.
Home-page: https://github.com/KrishnaswamyLab/TPHATE
Author: Erica Busch, Krishnaswamy Lab, Yale University
Author-email: Erica Busch <ericalindseybusch@gmail.com>
Project-URL: Homepage, https://github.com/KrishnaswamyLab/TPHATE/
Project-URL: Bug Tracker, https://github.com/KrishnaswamyLab/TPHATE/issues
Classifier: Programming Language :: Python :: 3
Classifier: License :: OSI Approved :: GNU General Public License (GPL)
Classifier: Operating System :: OS Independent
Requires-Python: >=3.8
License-File: LICENSE.md
Requires-Dist: statsmodels>=0.13.5
Requires-Dist: pytest>=7.2.1
Requires-Dist: numpy>=1.16.0
Requires-Dist: scipy>=1.1.0
Requires-Dist: scikit-learn>=0.24
Requires-Dist: tasklogger>=1.0
Requires-Dist: graphtools>=1.5.3
Requires-Dist: matplotlib>=3.0
Requires-Dist: s_gd2>=1.8.1
Requires-Dist: pygsp
Requires-Dist: Deprecated
Dynamic: author
Dynamic: home-page
Dynamic: license-file
Dynamic: requires-python
